[
  {
    "id": "a06625d9-2fab-41ee-8333-187062c75c99",
    "keyword": "就活 グループワーク マナー 発言",
    "category": "就活マナー",
    "used": false,
    "sub_category": ""
  },
  {
    "id": "41898951-ba77-4a8d-b7f0-960f8e12abe6",
    "keyword": "就活 ビジネスマナー 基本 一覧",
    "category": "就活マナー",
    "used": false,
    "sub_category": ""
  },
  {
    "id": "0925f399-9bd6-41f3-8bd5-fcb588253203",
    "keyword": "就活 失礼 行動 NGリスト",
    "category": "就活マナー",
    "used": false,
    "sub_category": ""
  },
  {
    "id": "626c60a6-f009-4b27-9c4b-f68c21e99cd3",
    "keyword": "就活 企業 メール くる 返信 必要",
    "category": "就活マナー",
    "used": false,
    "sub_category": ""
  },
  {
    "id": "237b6074-bfa2-4942-a8c2-cf367d8fb35d",
    "keyword": "就活 電話 知らない 番号 出る",
    "category": "就活マナー",
    "used": false,
    "sub_category": ""
  },
  {
    "id": "42b1290b-c6a0-4f6c-b510-72e4e5f3714f",
    "keyword": "就活 内定 メール 返信 例文",
    "category": "就活マナー",
    "used": false,
    "sub_category": ""
  },
  {
    "id": "ddc956ea-8d00-4f25-814a-408e0b6ab6cc",
    "keyword": "就活 内定 電話 受け方 返事",
    "category": "就活マナー",
    "used": false,
    "sub_category": ""
  },
  {
    "id": "1127ea64-fa01-4379-86b1-5802cfae0196",
    "keyword": "就活 書類選考 通過 連絡 来ない",
    "category": "就活マナー",
    "used": false,
    "sub_category": ""
  },
  {
    "id": "9fa235ad-fbca-4828-9704-4afbb2a7f76e",
    "keyword": "就活 企業 個人情報 聞かれる 対応",
    "category": "就活マナー",
    "used": false,
    "sub_category": ""
  },
  {
    "id": "0c92f117-71c3-4603-98c1-5d2c4a6f5281",
    "keyword": "就活 お祈りメール 返信 必要",
    "category": "就活マナー",
    "used": false,
    "sub_category": ""
  },
  {
    "id": "68ecc4ae-7812-411c-8240-0257f8df5d7f",
    "keyword": "就活 総合職 転勤 嫌 対策",
    "category": "業界研究",
    "used": false,
    "sub_category": ""
  },
  {
    "id": "e69f94e0-d764-4caf-ae2d-a8fe7d1af53a",
    "keyword": "就活 職種 一覧 説明",
    "category": "業界研究",
    "used": false,
    "sub_category": ""
  },
  {
    "id": "5039fa06-0578-4dad-ac68-ee536be9f2b7",
    "keyword": "就活 総合職 一般職 違い",
    "category": "業界研究",
    "used": false,
    "sub_category": ""
  },
  {
    "id": "54ad995f-eb8e-4f1c-b0ab-f52341820a1a",
    "keyword": "サービス 業界 就活 難易度",
    "category": "業界研究",
    "used": false,
    "sub_category": ""
  },
  {
    "id": "33830567-6820-45f1-908f-fe9301dfed55",
    "keyword": "HRテック 業界 就活 注目",
    "category": "業界研究",
    "used": false,
    "sub_category": ""
  },
  {
    "id": "29ca48ed-92e0-435c-8099-53000a629102",
    "keyword": "フードテック 業界 就活 注目",
    "category": "業界研究",
    "used": false,
    "sub_category": ""
  },
  {
    "id": "8929a97d-21b9-43d8-be10-fcea6367a89e",
    "keyword": "農業 業界 就活 特徴 就職 難易度",
    "category": "業界研究",
    "used": false,
    "sub_category": ""
  },
  {
    "id": "f514096b-5936-4ce3-90dd-b311c33d43e9",
    "keyword": "ブライダル 業界 就活 特徴 将来性",
    "category": "業界研究",
    "used": false,
    "sub_category": ""
  },
  {
    "id": "16ada40d-b449-4d03-aca5-f8b8a0eca647",
    "keyword": "コスメ 美容 業界 就活 特徴",
    "category": "業界研究",
    "used": false,
    "sub_category": ""
  },
  {
    "id": "38d54bc6-d256-4713-8574-ac391ce693e8",
    "keyword": "アパレル 業界 就活 年収 将来性",
    "category": "業界研究",
    "used": false,
    "sub_category": ""
  }
]