[
  {
    "id": "6bdbbd2a-ad88-446d-ad36-c08873422fd5",
    "keyword": "カナダ ワーホリ 就職 新卒",
    "category": "留学・海外就活",
    "used": false,
    "sub_category": ""
  },
  {
    "id": "181f61e5-0510-4c0d-9548-458e18cc7fc0",
    "keyword": "イギリス 就職 日本人 新卒 方法",
    "category": "留学・海外就活",
    "used": false,
    "sub_category": ""
  },
  {
    "id": "bdae20b2-1729-49ad-a8b8-5a2ac40c951e",
    "keyword": "アメリカ 就職 日本人 新卒 難易度",
    "category": "留学・海外就活",
    "used": false,
    "sub_category": ""
  },
  {
    "id": "7db57966-6874-41d9-bc64-24076e67bd95",
    "keyword": "オンライン面接 注意点",
    "category": "面接対策",
    "used": false,
    "sub_category": ""
  },
  {
    "id": "a6f94f8f-9c30-4517-86d9-5267c4160632",
    "keyword": "オンライン面接 注意点 背景",
    "category": "面接対策",
    "used": false,
    "sub_category": ""
  },
  {
    "id": "22571625-b58e-43bf-999c-855d67399c86",
    "keyword": "面接 シャツ 色 就活",
    "category": "面接対策",
    "used": false,
    "sub_category": ""
  },
  {
    "id": "53be8a54-8aef-4022-b3d3-057771dacfac",
    "keyword": "面接 ネクタイ 色 就活",
    "category": "面接対策",
    "used": false,
    "sub_category": ""
  },
  {
    "id": "4170d2b4-edd8-4a93-be17-cb26c2df4bb0",
    "keyword": "面接 メイク 就活 女性",
    "category": "面接対策",
    "used": false,
    "sub_category": ""
  },
  {
    "id": "d01b9305-d5c6-43d9-b359-a1d35f78d71e",
    "keyword": "面接 靴 選び方 就活",
    "category": "面接対策",
    "used": false,
    "sub_category": ""
  },
  {
    "id": "259e7580-a8da-4564-8bb3-4ead1f10caea",
    "keyword": "面接 バッグ 選び方 就活",
    "category": "面接対策",
    "used": false,
    "sub_category": ""
  },
  {
    "id": "163cb851-6238-4a84-a50e-2b9a111838af",
    "keyword": "面接 アクセサリー 就活 マナー",
    "category": "面接対策",
    "used": false,
    "sub_category": ""
  },
  {
    "id": "6ba82b00-ac45-40f9-b19e-8b8d857a1257",
    "keyword": "面接 香水 注意点",
    "category": "面接対策",
    "used": false,
    "sub_category": ""
  },
  {
    "id": "403e3f6c-94f9-4b51-8148-3d7e0fcb3cea",
    "keyword": "面接 声 大きさ 話し方",
    "category": "面接対策",
    "used": false,
    "sub_category": ""
  },
  {
    "id": "ad0e0f3e-bb37-4404-a405-b57140b4e4c4",
    "keyword": "面接 笑顔 作り方 コツ",
    "category": "面接対策",
    "used": false,
    "sub_category": ""
  },
  {
    "id": "5398e3f5-fbf2-40c0-8b50-6255a4387d68",
    "keyword": "集団面接 対策 個別との違い",
    "category": "面接対策",
    "used": false,
    "sub_category": ""
  },
  {
    "id": "93979dc6-b6e7-4887-98fe-3ee5d43bc0da",
    "keyword": "面接 日程 変更 メール 例文",
    "category": "面接対策",
    "used": false,
    "sub_category": ""
  },
  {
    "id": "81a37df8-3e30-4875-b8f6-787d9819a49c",
    "keyword": "面接 複数日程 候補日 メール 返し方",
    "category": "面接対策",
    "used": false,
    "sub_category": ""
  },
  {
    "id": "1ea0d264-0a0d-46f0-b583-9e297e8cace8",
    "keyword": "面接 結果 連絡 遅い 理由",
    "category": "面接対策",
    "used": false,
    "sub_category": ""
  },
  {
    "id": "32a71155-1fb6-4396-81cb-bee68bfa268f",
    "keyword": "面接 通過 サイン 見分け方",
    "category": "面接対策",
    "used": false,
    "sub_category": ""
  },
  {
    "id": "3ebacf45-c42a-4a3a-a08c-4c374b4cc3f2",
    "keyword": "面接 落ちる 理由 わからない",
    "category": "面接対策",
    "used": false,
    "sub_category": ""
  }
]